maya_azure_storage/__init__.py
maya_azure_storage/azure_blob_storage.py
maya_azure_storage-0.1.0.dist-info/METADATA
maya_azure_storage-0.1.0.dist-info/WHEEL
maya_azure_storage-0.1.0.dist-info/top_level.txt
maya_azure_storage-0.1.0.dist-info/RECORD
