Metadata-Version: 2.1
Name: maya_azure_storage
Version: 0.1.0
Summary: A package for handling maya azure blob storage operations
Home-page: https://github.com/Trimble-Construction/project-maya/tree/dev/Cloud/AzureBlobStorage
Author: Asifaa Sulthana
Author-email: asifaa_sulthanan@trimble.com
Classifier: Programming Language :: Python :: 3
Classifier: License :: OSI Approved :: MIT License
Classifier: Operating System :: OS Independent
Requires-Python: >=3.6
Requires-Dist: pika
